LICENSE
README.md
pyproject.toml
setup.py
pycroquet/__init__.py
pycroquet/classes.py
pycroquet/cli.py
pycroquet/constants.py
pycroquet/countwriter.py
pycroquet/dualguide.py
pycroquet/htscomm.py
pycroquet/libparser.py
pycroquet/main.py
pycroquet/merge.py
pycroquet/readparser.py
pycroquet/readwriter.py
pycroquet/sge.py
pycroquet/singleguide.py
pycroquet/targets.py
pycroquet/tools.py
pycroquet.egg-info/PKG-INFO
pycroquet.egg-info/SOURCES.txt
pycroquet.egg-info/dependency_links.txt
pycroquet.egg-info/entry_points.txt
pycroquet.egg-info/requires.txt
pycroquet.egg-info/top_level.txt
pycroquet/resources/library.yaml