Metadata-Version: 2.1
Name: pycroquet
Version: 1.5.1
Summary: python Crispr Read to Oligo QUantification Enhancement Tool
Home-page: https://github.com/cancerit/pycroquet
Author: Keiran M Raine
Author-email: cgphelp@sanger.ac.uk
License: AGPL-3.0
Platform: UNKNOWN
Requires-Python: >= 3.9
License-File: LICENSE
